[
  {},
  {},
  {
    "date": "2023-05-02T00:00:00Z",
    "VSCode-Znuny": "3"
  },
  {
    "date": "2023-05-03T00:00:00Z",
    "VSCode-Znuny": "4"
  },
  {
    "date": "2023-05-08T00:00:00Z",
    "VSCode-Znuny": "8"
  },
  {
    "date": "2023-05-09T00:00:00Z",
    "VSCode-Znuny": "11"
  },
  {
    "date": "2023-05-12T00:00:00Z",
    "VSCode-Znuny": "12"
  },
  {
    "date": "2023-05-15T00:00:00Z",
    "VSCode-Znuny": "13"
  },
  {
    "date": "2023-05-17T00:00:00Z",
    "VSCode-Znuny": "18"
  },
  {
    "date": "2023-05-22T00:00:00Z",
    "VSCode-Znuny": "19"
  },
  {
    "date": "2023-05-26T00:00:00Z",
    "VSCode-Znuny": "21"
  },
  {
    "date": "2023-05-29T00:00:00Z",
    "VSCode-Znuny": "23"
  },
  {
    "date": "2023-05-31T00:00:00Z",
    "VSCode-Znuny": "24"
  },
  {
    "date": "2023-06-03T00:00:00Z",
    "VSCode-Znuny": "25"
  },
  {
    "date": "2023-06-06T00:00:00Z",
    "VSCode-Znuny": "26"
  },
  {
    "date": "2023-06-07T00:00:00Z",
    "VSCode-Znuny": "27"
  },
  {
    "date": "2023-06-14T00:00:00Z",
    "VSCode-Znuny": "28"
  },
  {
    "date": "2023-06-19T00:00:00Z",
    "VSCode-Znuny": "29"
  },
  {
    "date": "2023-06-29T00:00:00Z",
    "VSCode-Znuny": "30"
  },
  {
    "date": "2023-07-03T00:00:00Z",
    "VSCode-Znuny": "31"
  },
  {
    "date": "2023-07-04T00:00:00Z",
    "VSCode-AddFolderToWorkspace": "2"
  },
  {
    "date": "2023-07-06T00:00:00Z",
    "VSCode-AddFolderToWorkspace": "3",
    "VSCode-Znuny": "32"
  },
  {
    "date": "2023-07-07T00:00:00Z",
    "VSCode-AddFolderToWorkspace": "5"
  },
  {
    "date": "2023-07-09T00:00:00Z",
    "VSCode-Znuny": "33"
  },
  {
    "date": "2023-07-11T00:00:00Z",
    "VSCode-AddFolderToWorkspace": "6"
  },
  {
    "date": "2023-07-21T00:00:00Z",
    "VSCode-AddFolderToWorkspace": "7"
  },
  {
    "date": "2023-07-24T00:00:00Z",
    "VSCode-AddFolderToWorkspace": "8"
  },
  {
    "date": "2023-07-25T00:00:00Z",
    "VSCode-AddFolderToWorkspace": "9"
  },
  {
    "date": "2023-07-27T00:00:00Z",
    "VSCode-Znuny": "34"
  },
  {
    "date": "2023-07-31T00:00:00Z",
    "VSCode-AddFolderToWorkspace": "10",
    "VSCode-QuoteWithMarker": "1"
  },
  {
    "date": "2023-08-03T00:00:00Z",
    "VSCode-Znuny": "35"
  },
  {
    "date": "2023-08-06T00:00:00Z",
    "VSCode-AddFolderToWorkspace": "11"
  },
  {
    "date": "2023-08-16T00:00:00Z",
    "VSCode-AddFolderToWorkspace": "12"
  },
  {
    "date": "2023-08-18T00:00:00Z",
    "VSCode-Znuny": "36"
  },
  {
    "date": "2023-08-20T00:00:00Z",
    "VSCode-Znuny": "37"
  },
  {
    "date": "2023-08-21T00:00:00Z",
    "VSCode-AddFolderToWorkspace": "13",
    "VSCode-Znuny": "38"
  },
  {
    "date": "2023-08-24T00:00:00Z",
    "VSCode-GitHubFileFetcher": "1"
  },
  {
    "date": "2023-08-25T00:00:00Z",
    "VSCode-GitHubFileFetcher": "2"
  },
  {
    "date": "2023-08-26T00:00:00Z",
    "VSCode-QuoteWithMarker": "2",
    "VSCode-Znuny": "39"
  },
  {
    "date": "2023-08-27T00:00:00Z",
    "VSCode-Znuny": "40"
  },
  {
    "date": "2023-08-28T00:00:00Z",
    "VSCode-AddFolderToWorkspace": "15",
    "VSCode-GitHubFileFetcher": "3"
  },
  {
    "date": "2023-08-29T00:00:00Z",
    "VSCode-GitHubFileFetcher": "4",
    "VSCode-Znuny": "42"
  },
  {
    "date": "2023-08-30T00:00:00Z",
    "VSCode-GitHubFileFetcher": "6"
  },
  {
    "date": "2023-08-31T00:00:00Z",
    "VSCode-Znuny": "44"
  },
  {
    "date": "2023-09-01T00:00:00Z",
    "VSCode-QuoteWithMarker": "3"
  },
  {
    "date": "2023-09-04T00:00:00Z",
    "VSCode-GitHubFileFetcher": "7"
  },
  {
    "date": "2023-09-05T00:00:00Z",
    "VSCode-GitHubFileFetcher": "8",
    "VSCode-QuoteWithMarker": "4"
  },
  {
    "date": "2023-09-06T00:00:00Z",
    "VSCode-AddFolderToWorkspace": "16"
  },
  {
    "date": "2023-09-07T00:00:00Z",
    "VSCode-AddFolderToWorkspace": "17",
    "VSCode-GitHubFileFetcher": "11"
  },
  {
    "date": "2023-09-11T00:00:00Z",
    "VSCode-GitHubFileFetcher": "12"
  },
  {
    "date": "2023-09-14T00:00:00Z",
    "VSCode-QuoteWithMarker": "5"
  },
  {
    "date": "2023-09-16T00:00:00Z",
    "VSCode-AddFolderToWorkspace": "18"
  },
  {
    "date": "2023-09-18T00:00:00Z",
    "VSCode-AddFolderToWorkspace": "19"
  },
  {
    "date": "2023-09-20T00:00:00Z",
    "VSCode-GitHubFileFetcher": "13"
  },
  {
    "date": "2023-09-22T00:00:00Z",
    "VSCode-Znuny": "46"
  },
  {
    "date": "2023-09-25T00:00:00Z",
    "VSCode-AddFolderToWorkspace": "20"
  },
  {
    "date": "2023-09-26T00:00:00Z",
    "VSCode-GitHubFileFetcher": "14"
  },
  {
    "date": "2023-09-27T00:00:00Z",
    "VSCode-AddFolderToWorkspace": "21",
    "VSCode-Znuny": "47"
  },
  {
    "date": "2023-09-28T00:00:00Z",
    "VSCode-Znuny": "48"
  },
  {
    "date": "2023-09-29T00:00:00Z",
    "VSCode-AddFolderToWorkspace": "22",
    "VSCode-GitHubFileFetcher": "16"
  },
  {
    "date": "2023-09-30T00:00:00Z",
    "VSCode-Znuny": "49"
  },
  {
    "date": "2023-10-02T00:00:00Z",
    "VSCode-GitHubFileFetcher": "18"
  },
  {
    "date": "2023-10-03T00:00:00Z",
    "VSCode-GitHubFileFetcher": "19"
  },
  {
    "date": "2023-10-04T00:00:00Z",
    "VSCode-GitHubFileFetcher": "21"
  },
  {
    "date": "2023-10-05T00:00:00Z",
    "VSCode-GitHubFileFetcher": "22",
    "VSCode-QuoteWithMarker": "6"
  },
  {
    "date": "2023-10-06T00:00:00Z",
    "VSCode-GitHubFileFetcher": "23"
  },
  {
    "date": "2023-10-09T00:00:00Z",
    "VSCode-QuoteWithMarker": "7"
  },
  {
    "date": "2023-10-10T00:00:00Z",
    "VSCode-AddFolderToWorkspace": "23",
    "VSCode-GitHubFileFetcher": "25"
  },
  {
    "date": "2023-10-11T00:00:00Z",
    "VSCode-AddFolderToWorkspace": "24"
  },
  {
    "date": "2023-10-14T00:00:00Z",
    "VSCode-GitHubFileFetcher": "26"
  },
  {
    "date": "2023-10-15T00:00:00Z",
    "VSCode-GitHubFileFetcher": "27"
  },
  {
    "date": "2023-10-16T00:00:00Z",
    "VSCode-GitHubFileFetcher": "28"
  },
  {
    "date": "2023-10-17T00:00:00Z",
    "VSCode-GitHubFileFetcher": "30"
  },
  {
    "date": "2023-10-19T00:00:00Z",
    "VSCode-QuoteWithMarker": "8"
  },
  {
    "date": "2023-10-20T00:00:00Z",
    "VSCode-Znuny": "50"
  },
  {
    "date": "2023-10-21T00:00:00Z",
    "VSCode-GitHubFileFetcher": "33"
  },
  {
    "date": "2023-10-23T00:00:00Z",
    "VSCode-AddFolderToWorkspace": "25",
    "VSCode-Znuny": "52"
  },
  {
    "date": "2023-10-24T00:00:00Z",
    "VSCode-AddFolderToWorkspace": "26",
    "VSCode-Znuny": "54"
  },
  {
    "date": "2023-10-25T00:00:00Z",
    "VSCode-GitHubFileFetcher": "35",
    "VSCode-Znuny": "55"
  },
  {
    "date": "2023-10-26T00:00:00Z",
    "VSCode-GitHubFileFetcher": "36"
  },
  {
    "date": "2023-10-26T00:00:00Z",
    "VSCode-QuoteWithMarker": "9"
  },
  {
    "date": "2023-10-27T00:00:00Z",
    "VSCode-GitHubFileFetcher": "37",
    "VSCode-QuoteWithMarker": "11"
  },
  {
    "date": "2023-10-29T00:00:00Z",
    "VSCode-GitHubFileFetcher": "38"
  },
  {
    "date": "2023-10-30T00:00:00Z",
    "VSCode-AddFolderToWorkspace": "27"
  },
  {
    "date": "2023-10-31T00:00:00Z",
    "VSCode-QuoteWithMarker": "12"
  },
  {
    "date": "2023-11-01T00:00:00Z",
    "VSCode-AddFolderToWorkspace": "28"
  },
  {
    "date": "2023-11-03T00:00:00Z",
    "VSCode-GitHubFileFetcher": "39"
  },
  {
    "date": "2023-11-04T00:00:00Z",
    "VSCode-GitHubFileFetcher": "40",
    "VSCode-QuoteWithMarker": "13"
  },
  {
    "date": "2023-11-06T00:00:00Z",
    "VSCode-AddFolderToWorkspace": "29"
  },
  {
    "date": "2023-11-07T00:00:00Z",
    "VSCode-AddFolderToWorkspace": "31"
  },
  {
    "date": "2023-11-08T00:00:00Z",
    "VSCode-AddFolderToWorkspace": "32",
    "VSCode-GitHubFileFetcher": "44"
  },
  {
    "date": "2023-11-09T00:00:00Z",
    "VSCode-AddFolderToWorkspace": "33",
    "VSCode-GitHubFileFetcher": "45"
  },
  {
    "date": "2023-11-10T00:00:00Z",
    "VSCode-GitHubFileFetcher": "46"
  },
  {
    "date": "2023-11-12T00:00:00Z",
    "VSCode-GitHubFileFetcher": "47"
  },
  {
    "date": "2023-11-15T00:00:00Z",
    "VSCode-GitHubFileFetcher": "49"
  },
  {
    "date": "2023-11-16T00:00:00Z",
    "VSCode-AddFolderToWorkspace": "35"
  },
  {
    "date": "2023-11-17T00:00:00Z",
    "VSCode-GitHubFileFetcher": "50"
  },
  {
    "date": "2023-11-18T00:00:00Z",
    "VSCode-Znuny": "58"
  },
  {
    "date": "2023-11-19T00:00:00Z",
    "VSCode-AddFolderToWorkspace": "36",
    "VSCode-Znuny": "59"
  },
  {
    "date": "2023-11-20T00:00:00Z",
    "VSCode-GitHubFileFetcher": "52"
  },
  {
    "date": "2023-11-21T00:00:00Z",
    "VSCode-Znuny": "61"
  },
  {
    "date": "2023-11-23T00:00:00Z",
    "VSCode-AddFolderToWorkspace": "37",
    "VSCode-Znuny": "62"
  },
  {
    "date": "2023-11-25T00:00:00Z",
    "VSCode-AddFolderToWorkspace": "38",
    "VSCode-GitHubFileFetcher": "53"
  },
  {
    "date": "2023-11-26T00:00:00Z",
    "VSCode-GitHubFileFetcher": "54",
    "VSCode-QuoteWithMarker": "14"
  },
  {
    "date": "2023-11-27T00:00:00Z",
    "VSCode-GitHubFileFetcher": "59",
    "VSCode-QuoteWithMarker": "19"
  },
  {
    "date": "2023-11-28T00:00:00Z",
    "VSCode-AddFolderToWorkspace": "39",
    "VSCode-GitHubFileFetcher": "60",
    "VSCode-QuoteWithMarker": "20"
  },
  {
    "date": "2023-11-29T00:00:00Z",
    "VSCode-AddFolderToWorkspace": "40",
    "VSCode-GitHubFileFetcher": "63",
    "VSCode-QuoteWithMarker": "23"
  },
  {
    "date": "2023-12-03T00:00:00Z",
    "VSCode-AddFolderToWorkspace": "41",
    "VSCode-GitHubFileFetcher": "64"
  },
  {
    "date": "2023-12-05T00:00:00Z",
    "VSCode-AddFolderToWorkspace": "42",
    "VSCode-GitHubFileFetcher": "66",
    "VSCode-QuoteWithMarker": "25"
  },
  {
    "date": "2023-12-06T00:00:00Z",
    "VSCode-AddFolderToWorkspace": "43",
    "VSCode-GitHubFileFetcher": "67"
  },
  {
    "date": "2023-12-08T00:00:00Z",
    "VSCode-AddFolderToWorkspace": "44"
  },
  {
    "date": "2023-12-09T00:00:00Z",
    "VSCode-GitHubFileFetcher": "68"
  },
  {
    "date": "2023-12-10T00:00:00Z",
    "VSCode-GitHubFileFetcher": "71",
    "VSCode-QuoteWithMarker": "26"
  },
  {
    "date": "2023-12-11T00:00:00Z",
    "VSCode-AddFolderToWorkspace": "45",
    "VSCode-GitHubFileFetcher": "73"
  },
  {
    "date": "2023-12-12T00:00:00Z",
    "VSCode-QuoteWithMarker": "27"
  },
  {
    "date": "2023-12-13T00:00:00Z",
    "VSCode-AddFolderToWorkspace": "46",
    "VSCode-GitHubFileFetcher": "77",
    "VSCode-QuoteWithMarker": "30"
  },
  {
    "date": "2023-12-14T00:00:00Z",
    "VSCode-AddFolderToWorkspace": "47"
  },
  {
    "date": "2023-12-15T00:00:00Z",
    "VSCode-AddFolderToWorkspace": "48",
    "VSCode-GitHubFileFetcher": "78"
  },
  {
    "date": "2023-12-17T00:00:00Z",
    "VSCode-AddFolderToWorkspace": "49",
    "VSCode-GitHubFileFetcher": "79"
  },
  {
    "date": "2023-12-18T00:00:00Z",
    "VSCode-AddFolderToWorkspace": "50",
    "VSCode-GitHubFileFetcher": "81"
  },
  {
    "date": "2023-12-19T00:00:00Z",
    "VSCode-AddFolderToWorkspace": "52",
    "VSCode-GitHubFileFetcher": "82"
  },
  {
    "date": "2023-12-20T00:00:00Z",
    "VSCode-GitHubFileFetcher": "83"
  },
  {
    "date": "2023-12-21T00:00:00Z",
    "VSCode-AddFolderToWorkspace": "53",
    "VSCode-GitHubFileFetcher": "84"
  },
  {
    "date": "2023-12-22T00:00:00Z",
    "VSCode-GitHubFileFetcher": "86",
    "VSCode-QuoteWithMarker": "31"
  },
  {
    "date": "2023-12-23T00:00:00Z",
    "VSCode-GitHubFileFetcher": "87",
    "VSCode-QuoteWithMarker": "32"
  },
  {
    "date": "2023-12-25T00:00:00Z",
    "VSCode-GitHubFileFetcher": "89"
  },
  {
    "date": "2023-12-26T00:00:00Z",
    "VSCode-GitHubFileFetcher": "90",
    "VSCode-QuoteWithMarker": "33"
  },
  {
    "date": "2023-12-28T00:00:00Z",
    "VSCode-GitHubFileFetcher": "93",
    "VSCode-QuoteWithMarker": "34"
  },
  {
    "date": "2023-12-30T00:00:00Z",
    "VSCode-GitHubFileFetcher": "95"
  },
  {
    "date": "2023-12-31T00:00:00Z",
    "VSCode-AddFolderToWorkspace": "54",
    "VSCode-GitHubFileFetcher": "96",
    "VSCode-QuoteWithMarker": "35"
  },
  {
    "date": "2024-01-01T00:00:00Z",
    "VSCode-GitHubFileFetcher": "97"
  },
  {
    "date": "2024-01-04T00:00:00Z",
    "VSCode-GitHubFileFetcher": "98",
    "VSCode-QuoteWithMarker": "36",
    "VSCode-Znuny": "63"
  },
  {
    "date": "2024-01-05T00:00:00Z",
    "VSCode-AddFolderToWorkspace": "55",
    "VSCode-GitHubFileFetcher": "99",
    "VSCode-QuoteWithMarker": "37"
  },
  {
    "date": "2024-01-06T00:00:00Z",
    "VSCode-GitHubFileFetcher": "100"
  },
  {
    "date": "2024-01-08T00:00:00Z",
    "VSCode-AddFolderToWorkspace": "59",
    "VSCode-GitHubFileFetcher": "101",
    "VSCode-QuoteWithMarker": "38"
  },
  {
    "date": "2024-01-09T00:00:00Z",
    "VSCode-AddFolderToWorkspace": "60",
    "VSCode-GitHubFileFetcher": "102"
  },
  {
    "date": "2024-01-11T00:00:00Z",
    "VSCode-GitHubFileFetcher": "103"
  },
  {
    "date": "2024-01-13T00:00:00Z",
    "VSCode-AddFolderToWorkspace": "61",
    "VSCode-GitHubFileFetcher": "104"
  },
  {
    "date": "2024-01-14T00:00:00Z",
    "VSCode-GitHubFileFetcher": "105"
  },
  {
    "date": "2024-01-15T00:00:00Z",
    "VSCode-GitHubFileFetcher": "107"
  },
  {
    "date": "2024-01-16T00:00:00Z",
    "VSCode-QuoteWithMarker": "39",
    "VSCode-Znuny": "64"
  },
  {
    "date": "2024-01-17T00:00:00Z",
    "VSCode-AddFolderToWorkspace": "62",
    "VSCode-GitHubFileFetcher": "109"
  },
  {
    "date": "2024-01-18T00:00:00Z",
    "VSCode-AddFolderToWorkspace": "64",
    "VSCode-GitHubFileFetcher": "110",
    "VSCode-QuoteWithMarker": "40",
    "VSCode-Znuny": "65"
  },
  {
    "date": "2024-01-19T00:00:00Z",
    "VSCode-AddFolderToWorkspace": "65",
    "VSCode-GitHubFileFetcher": "112",
    "VSCode-QuoteWithMarker": "41"
  },
  {
    "date": "2024-01-20T00:00:00Z",
    "VSCode-GitHubFileFetcher": "113",
    "VSCode-Znuny": "66"
  },
  {
    "date": "2024-01-21T00:00:00Z",
    "VSCode-AddFolderToWorkspace": "66",
    "VSCode-GitHubFileFetcher": "114"
  },
  {
    "date": "2024-01-22T00:00:00Z",
    "VSCode-GitHubFileFetcher": "116",
    "VSCode-Znuny": "67"
  },
  {
    "date": "2024-01-27T00:00:00Z",
    "VSCode-GitHubFileFetcher": "118"
  },
  {
    "date": "2024-01-29T00:00:00Z",
    "VSCode-GitHubFileFetcher": "119"
  },
  {
    "date": "2024-01-30T00:00:00Z",
    "VSCode-AddFolderToWorkspace": "67",
    "VSCode-GitHubFileFetcher": "120"
  },
  {
    "date": "2024-01-31T00:00:00Z",
    "VSCode-AddFolderToWorkspace": "73",
    "VSCode-GitHubFileFetcher": "121",
    "VSCode-MyExtensionPack": "5",
    "VSCode-QuoteWithMarker": "47",
    "VSCode-Znuny": "73"
  },
  {
    "date": "2024-02-01T00:00:00Z",
    "VSCode-AddFolderToWorkspace": "75",
    "VSCode-RainbowColors": "2"
  },
  {
    "date": "2024-02-02T00:00:00Z",
    "VSCode-GitHubFileFetcher": "122"
  },
  {
    "date": "2024-02-03T00:00:00Z",
    "VSCode-RainbowColors": "3"
  },
  {
    "date": "2024-02-04T00:00:00Z",
    "VSCode-AddFolderToWorkspace": "77"
  },
  {
    "date": "2024-02-05T00:00:00Z",
    "VSCode-AddFolderToWorkspace": "79",
    "VSCode-MyExtensionPack": "6",
    "VSCode-QuoteWithMarker": "48"
  },
  {
    "date": "2024-02-06T00:00:00Z",
    "VSCode-AddFolderToWorkspace": "80",
    "VSCode-GitHubFileFetcher": "124",
    "VSCode-RainbowColors": "5",
    "VSCode-Znuny": "74"
  },
  {
    "date": "2024-02-07T00:00:00Z",
    "VSCode-RainbowColors": "6"
  },
  {
    "date": "2024-02-08T00:00:00Z",
    "VSCode-GitHubFileFetcher": "125",
    "VSCode-RainbowColors": "7"
  },
  {
    "date": "2024-02-09T00:00:00Z",
    "VSCode-AddFolderToWorkspace": "81",
    "VSCode-GitHubFileFetcher": "126",
    "VSCode-QuoteWithMarker": "49"
  },
  {
    "date": "2024-02-11T00:00:00Z",
    "VSCode-GitHubFileFetcher": "127",
    "VSCode-RainbowColors": "8"
  },
  {
    "date": "2024-02-12T00:00:00Z",
    "VSCode-AddFolderToWorkspace": "82"
  },
  {
    "date": "2024-02-13T00:00:00Z",
    "VSCode-AddFolderToWorkspace": "83",
    "VSCode-GitHubFileFetcher": "128"
  },
  {
    "date": "2024-02-15T00:00:00Z",
    "VSCode-GitHubFileFetcher": "129"
  },
  {
    "date": "2024-02-16T00:00:00Z",
    "VSCode-GitHubFileFetcher": "130",
    "VSCode-QuoteWithMarker": "50"
  },
  {
    "date": "2024-02-17T00:00:00Z",
    "VSCode-GitHubFileFetcher": "131",
    "VSCode-QuoteWithMarker": "52"
  },
  {
    "date": "2024-02-18T00:00:00Z",
    "VSCode-AddFolderToWorkspace": "84",
    "VSCode-RainbowColors": "9"
  },
  {
    "date": "2024-02-19T00:00:00Z",
    "VSCode-GitHubFileFetcher": "132"
  },
  {
    "date": "2024-02-19T00:00:00Z",
    "VSCode-RainbowColors": "10",
    "VSCode-Znuny": "75"
  },
  {
    "date": "2024-02-20T00:00:00Z",
    "VSCode-GitHubFileFetcher": "133",
    "VSCode-RainbowColors": "11"
  },
  {
    "date": "2024-02-21T00:00:00Z",
    "VSCode-GitHubFileFetcher": "135"
  }
]
